{
  "slug": "trey_turner_and_cody_haynes-better_late_than_never",
  "title": "Better Late Than Never",
  "mixedBy": "Trey Turner & Cody Haynes",
  "djs": ["Trey Turner", "Cody Haynes"],
  "releaseDate": "2009-07-31T12:00:00+00:00",
  "description": "Tech and glitchy midtempo breakbeats highlighted by some interesting MC work",
  "duration": "1:04:40",
  "filename": "2009_07_31-trey_turner_and_cody_haynes-better_late_than_never-v0.mp3",
  "filesize": 119087339,
  "mixcloudSlug": "nurevolution%2Ftrey-turner-cody-haynes-better-late-than-never",
  "spotifyPlaylist": "0rNBnENhGguscaIxsyQ8ne",
  "coverArt": {
    "full": "2009_07_31-Trey_Turner_and_Cody_Haynes-Better_Late_Than_Never.jpg"
  },
  "tracklist": [
    {
      "artist": "Divinci",
      "title": "Gnat (Gnastie)",
      "startTime": "0:00"
    },
    {
      "artist": "Modeselektor",
      "title": "Das Claudia Woelkey Massa",
      "startTime": "4:15"
    },
    {
      "artist": "East Flatbush Project",
      "title": "Tried by 12 (Autechre)",
      "startTime": "7:21"
    },
    {
      "artist": "Take",
      "title": "Make Believe (Dimlite)",
      "startTime": "10:14"
    },
    {
      "artist": "Sixtoo",
      "title": "Jackals and Vipers in Envy of Man, Pt. 10",
      "startTime": "14:21"
    },
    {
      "artist": "Ra",
      "title": "Let The Wxfdswxc Hit'Em",
      "startTime": "17:45"
    },
    {
      "artist": "The Disciple Grin",
      "title": "Yoke",
      "startTime": "19:16"
    },
    {
      "artist": "Bit Meddler",
      "title": "Whitelabels",
      "startTime": "23:01"
    },
    {
      "artist": "Kristuit Salu",
      "title": "Conceptial Devaihdn",
      "startTime": "25:02"
    },
    {
      "artist": "Crystal Distortion",
      "title": "Hypnotism Hop",
      "startTime": "26:24"
    },
    {
      "artist": "Si Begg",
      "title": "Logan's Run 3000",
      "startTime": "29:31"
    },
    {
      "artist": "Si Begg",
      "title": "Control This Thing",
      "startTime": "33:33"
    },
    {
      "artist": "Breakbeatbuddha",
      "title": "Dissent",
      "startTime": "38:10"
    },
    {
      "artist": "Modeselektor",
      "title": "The Dark Side of the Sun ft. Puppetmastaz",
      "startTime": "43:13"
    },
    {
      "artist": "Cabbage Boy",
      "title": "Cutting Japan",
      "startTime": "46:46"
    },
    {
      "artist": "Bil Bless",
      "title": "CheeseHOG",
      "startTime": "48:21"
    },
    {
      "artist": "DJ Rupture",
      "title": "Bonechip",
      "startTime": "52:12"
    },
    {
      "artist": "El-P",
      "title": "Dead Disnee",
      "startTime": "55:51"
    },
    {
      "artist": "Shadow Huntaz",
      "title": "Medic",
      "startTime": "59:41"
    }
  ]
}
